synthgen/__init__.py
synthgen/core.py
synthgen/tabular.py
synthgen/utils.py
tests/__init__.py
tests/test_core.py
tests/test_tabular.py
synthro-0.1.0.dist-info/LICENSE.md
synthro-0.1.0.dist-info/METADATA
synthro-0.1.0.dist-info/WHEEL
synthro-0.1.0.dist-info/top_level.txt
synthro-0.1.0.dist-info/RECORD
